[{"verbalized_question": "What is the <debut team> of the <gridiron football player> whose <college> is <Hawaii> ?", "corrected_question": "For which teams did the Hawai graduated players play their first game?", "sparql_query": "SELECT DISTINCT ?uri WHERE { ?x <http://dbpedia.org/property/college> <http://dbpedia.org/resource/Hawaii> . ?x <http://dbpedia.org/ontology/debutTeam> ?uri  . ?x <http://www.w3.org/1999/02/22-rdf-syntax-ns#type> <http://dbpedia.org/ontology/Athlete>}", "training": {"http://dbpedia.org/resource/Hawaii": {"rel2": [[{"http://dbpedia.org/property/state": [[], []]}, {"http://dbpedia.org/property/sport": [["http://dbpedia.org/ontology/wikiPageLength", "http://dbpedia.org/property/wikiPageUsesTemplate", "http://dbpedia.org/ontology/wikiPageWikiLinkText", "http://xmlns.com/foaf/0.1/isPrimaryTopicOf", "http://dbpedia.org/ontology/wikiPageOutDegree"], ["http://dbpedia.org/ontology/genre", "http://dbpedia.org/property/sport"]]}], [{"http://dbpedia.org/property/workInstitution": [[], []]}, {"http://dbpedia.org/property/college": [["http://dbpedia.org/property/college", "http://dbpedia.org/ontology/college"], ["http://xmlns.com/foaf/0.1/primaryTopic", "http://dbpedia.org/ontology/wikiPageDisambiguates", "http://dbpedia.org/ontology/wikiPageWikiLink", "http://dbpedia.org/property/isCitedBy"]]}, {"http://dbpedia.org/ontology/college": [["http://dbpedia.org/property/college", "http://dbpedia.org/ontology/college"], ["http://xmlns.com/foaf/0.1/primaryTopic", "http://dbpedia.org/ontology/wikiPageDisambiguates", "http://dbpedia.org/ontology/wikiPageWikiLink", "http://dbpedia.org/property/isCitedBy"]]}, {"http://dbpedia.org/ontology/hometown": [["http://dbpedia.org/ontology/hometown", "http://dbpedia.org/property/homeTown"], ["http://dbpedia.org/ontology/musicalArtist", "http://dbpedia.org/ontology/formerBandMember", "http://dbpedia.org/ontology/wikiPageWikiLink", "http://dbpedia.org/property/pastMembers", "http://dbpedia.org/property/extra"]]}, {"http://dbpedia.org/property/hometown": [["http://dbpedia.org/property/hometown", "http://dbpedia.org/property/name"], ["http://xmlns.com/foaf/0.1/primaryTopic", "http://dbpedia.org/ontology/wikiPageRedirects", "http://dbpedia.org/ontology/wikiPageWikiLink", "http://dbpedia.org/property/isCitedBy"]]}]], "rel1": [["http://dbpedia.org/property/website", "http://dbpedia.org/property/meanelevus", "http://dbpedia.org/ontology/PopulatedPlace/areaTotal", "http://www.w3.org/ns/prov#wasDerivedFrom", "http://dbpedia.org/ontology/demonym", "http://dbpedia.org/property/mammal", "http://dbpedia.org/ontology/wikiPageLength", "http://dbpedia.org/property/fish", "http://xmlns.com/foaf/0.1/isPrimaryTopicOf", "http://www.w3.org/2003/01/geo/wgs84_pos#lat", "http://dbpedia.org/property/lowestpoint", "http://dbpedia.org/property/tree", "http://dbpedia.org/ontology/areaTotal", "http://dbpedia.org/ontology/wikiPageID", "http://dbpedia.org/property/largestcity", "http://www.georss.org/georss/point", "http://dbpedia.org/property/flaglink", "http://dbpedia.org/property/waterareaus", "http://dbpedia.org/property/routeMarker", "http://www.w3.org/2000/01/rdf-schema#seeAlso", "http://dbpedia.org/ontology/wikiPageExternalLink", "http://dbpedia.org/property/quarter", "http://dbpedia.org/property/seallink", "http://dbpedia.org/property/lengthus", "http://dbpedia.org/ontology/wikiPageWikiLinkText", "http://dbpedia.org/property/years", "http://dbpedia.org/property/legislature", "http://dbpedia.org/ontology/country", "http://dbpedia.org/property/lieutenantGovernor", "http://dbpedia.org/property/governor", "http://www.w3.org/2003/01/geo/wgs84_pos#long", "http://dbpedia.org/property/quarterreleasedate", "http://dbpedia.org/ontology/areaLand", "http://dbpedia.org/property/southwest", "http://dbpedia.org/property/lowestelev", "http://dbpedia.org/property/wikiPageUsesTemplate", "http://dbpedia.org/property/landarea", "http://dbpedia.org/property/bird", "http://dbpedia.org/property/coatOfArms", "http://dbpedia.org/property/highestpoint", "http://dbpedia.org/property/former", "http://dbpedia.org/property/dance", "http://dbpedia.org/property/insect", "http://dbpedia.org/property/east", "http://dbpedia.org/property/north", "http://dbpedia.org/property/southeast", "http://dbpedia.org/property/2000densityus", "http://dbpedia.org/property/name", "http://dbpedia.org/ontology/wikiPageOutDegree", "http://dbpedia.org/property/instrument", "http://dbpedia.org/property/postalabbreviation", "http://dbpedia.org/property/upperhouse", "http://xmlns.com/foaf/0.1/homepage", "http://dbpedia.org/ontology/wikiPageRevisionID", "http://www.w3.org/2002/07/owl#sameAs", "http://dbpedia.org/property/latitude", "http://dbpedia.org/property/widthus", "http://dbpedia.org/property/motto", "http://dbpedia.org/property/lowerhouse", "http://dbpedia.org/property/mottoenglish", "http://dbpedia.org/property/waterarea", "http://dbpedia.org/property/nickname", "http://dbpedia.org/property/largestmetro", "http://www.w3.org/1999/02/22-rdf-syntax-ns#type", "http://dbpedia.org/ontology/capital", "http://dbpedia.org/property/othername", "http://dbpedia.org/property/capital", "http://dbpedia.org/ontology/minimumElevation", "http://dbpedia.org/ontology/areaWater", "http://dbpedia.org/property/highestelev", "http://xmlns.com/foaf/0.1/depiction", "http://dbpedia.org/property/stateanthem", "http://dbpedia.org/ontology/thumbnail", "http://dbpedia.org/property/fullname", "http://dbpedia.org/property/highestelevus", "http://dbpedia.org/property/tartan", "http://dbpedia.org/ontology/wikiPageWikiLink", "http://dbpedia.org/property/meanelev", "http://dbpedia.org/property/senators", "http://dbpedia.org/property/landareaus", "http://dbpedia.org/property/flag", "http://dbpedia.org/property/longitude", "http://dbpedia.org/property/timezone", "http://dbpedia.org/property/width", "http://dbpedia.org/ontology/maximumElevation", "http://www.w3.org/2002/07/owl#differentFrom", "http://dbpedia.org/property/totalareaus", "http://dbpedia.org/property/gemstone", "http://dbpedia.org/property/medianhouseholdincome", "http://dbpedia.org/property/totalarea", "http://dbpedia.org/ontology/abstract", "http://dbpedia.org/property/isocode", "http://purl.org/dc/terms/subject", "http://dbpedia.org/property/2000density", "http://dbpedia.org/property/state", "http://dbpedia.org/property/song", "http://dbpedia.org/property/pcwater", "http://dbpedia.org/property/admittancedate", "http://dbpedia.org/property/northeast", "http://www.w3.org/2000/01/rdf-schema#label", "http://dbpedia.org/ontology/language", "http://dbpedia.org/property/title", "http://dbpedia.org/property/length", "http://dbpedia.org/property/flower", "http://dbpedia.org/property/representative", "http://www.w3.org/2000/01/rdf-schema#comment", "http://dbpedia.org/property/sport", "http://dbpedia.org/property/northwest", "http://dbpedia.org/property/officiallang", "http://dbpedia.org/property/demonym", "http://dbpedia.org/property/south", "http://dbpedia.org/property/seal", "http://xmlns.com/foaf/0.1/name", "http://dbpedia.org/property/west", "http://dbpedia.org/property/lowestelevus", "http://dbpedia.org/property/2010pop"], ["http://dbpedia.org/property/placeOfDeath", "http://dbpedia.org/property/origin", "http://dbpedia.org/property/broadcastArea", "http://dbpedia.org/property/city", "http://dbpedia.org/ontology/garrison", "http://dbpedia.org/property/homeTown", "http://dbpedia.org/property/territory", "http://dbpedia.org/property/nation", "http://dbpedia.org/property/serviceArea", "http://dbpedia.org/property/birthPlace", "http://dbpedia.org/ontology/isPartOf", "http://dbpedia.org/ontology/nationality", "http://dbpedia.org/property/placeOfBirth", "http://dbpedia.org/property/hometown", "http://dbpedia.org/property/meetingPlace", "http://dbpedia.org/property/regionalScenes", "http://dbpedia.org/property/siteCityst", "http://dbpedia.org/property/nationality", "http://dbpedia.org/ontology/recordedIn", "http://dbpedia.org/property/venue", "http://dbpedia.org/property/space", "http://dbpedia.org/ontology/state", "http://dbpedia.org/ontology/college", "http://dbpedia.org/ontology/location", "http://dbpedia.org/property/countriesAffected", "http://dbpedia.org/ontology/wikiPageDisambiguates", "http://dbpedia.org/property/area", "http://dbpedia.org/ontology/hometown", "http://dbpedia.org/ontology/restingPlace", "http://dbpedia.org/ontology/spokenIn", "http://dbpedia.org/property/foundingLocation", "http://dbpedia.org/property/jurisdiction", "http://www.w3.org/2000/01/rdf-schema#seeAlso", "http://dbpedia.org/ontology/foundationPlace", "http://dbpedia.org/property/birthplace", "http://dbpedia.org/ontology/discoverer", "http://dbpedia.org/ontology/locatedInArea", "http://dbpedia.org/property/before", "http://dbpedia.org/property/placeOfBurial", "http://dbpedia.org/property/site", "http://dbpedia.org/ontology/producer", "http://dbpedia.org/ontology/country", "http://dbpedia.org/property/region", "http://dbpedia.org/property/workplaces", "http://dbpedia.org/property/home", "http://purl.org/linguistics/gold/hypernym", "http://dbpedia.org/property/discoverySite", "http://dbpedia.org/property/governingBody", "http://dbpedia.org/property/work", "http://dbpedia.org/property/origins", "http://dbpedia.org/property/country", "http://dbpedia.org/ontology/billed", "http://dbpedia.org/ontology/regionServed", "http://dbpedia.org/property/areaServed", "http://dbpedia.org/property/areasAffected", "http://xmlns.com/foaf/0.1/primaryTopic", "http://dbpedia.org/ontology/significantProject", "http://dbpedia.org/property/officialName", "http://dbpedia.org/property/client", "http://dbpedia.org/property/location", "http://dbpedia.org/property/states", "http://dbpedia.org/ontology/deathPlace", "http://dbpedia.org/property/publisher", "http://dbpedia.org/ontology/genre", "http://dbpedia.org/property/geoFeatures", "http://dbpedia.org/ontology/launchSite", "http://dbpedia.org/ontology/wikiPageRedirects", "http://dbpedia.org/property/aux", "http://dbpedia.org/property/deathPlace", "http://dbpedia.org/property/garrison", "http://dbpedia.org/property/areas", "http://dbpedia.org/property/recorded", "http://dbpedia.org/ontology/majorShrine", "http://dbpedia.org/property/producer", "http://dbpedia.org/ontology/origin", "http://dbpedia.org/property/imageCaption", "http://dbpedia.org/property/residence", "http://dbpedia.org/ontology/significantBuilding", "http://dbpedia.org/property/billed", "http://dbpedia.org/property/sites", "http://dbpedia.org/property/pbSite", "http://dbpedia.org/property/placeofburial", "http://dbpedia.org/property/majorShrine", "http://dbpedia.org/property/withdraws", "http://dbpedia.org/property/owner", "http://dbpedia.org/property/title", "http://dbpedia.org/property/archipelago", "http://dbpedia.org/property/ideology", "http://xmlns.com/foaf/0.1/depiction", "http://dbpedia.org/property/fightingOutOf", "http://dbpedia.org/ontology/archipelago", "http://dbpedia.org/property/observedby", "http://dbpedia.org/ontology/city", "http://dbpedia.org/property/recordLocation", "http://dbpedia.org/property/subdivisionName", "http://dbpedia.org/ontology/ethnicity", "http://dbpedia.org/property/headquarters", "http://dbpedia.org/ontology/homeport", "http://dbpedia.org/property/highestLocation", "http://dbpedia.org/property/popplace", "http://dbpedia.org/ontology/wikiPageWikiLink", "http://dbpedia.org/ontology/owner", "http://dbpedia.org/property/destination", "http://dbpedia.org/property/previousLocations", "http://dbpedia.org/ontology/governingBody", "http://dbpedia.org/ontology/birthPlace", "http://dbpedia.org/property/stadium", "http://dbpedia.org/property/place", "http://dbpedia.org/property/college", "http://dbpedia.org/property/debuts", "http://dbpedia.org/property/territorialExtent", "http://dbpedia.org/ontology/jurisdiction", "http://dbpedia.org/property/isCitedBy", "http://dbpedia.org/property/transCoverage", "http://dbpedia.org/property/caption", "http://dbpedia.org/ontology/architect", "http://dbpedia.org/ontology/nearestCity", "http://dbpedia.org/ontology/child", "http://dbpedia.org/property/workInstitution", "http://www.w3.org/2002/07/owl#differentFrom", "http://dbpedia.org/property/restingplace", "http://dbpedia.org/property/locations", "http://dbpedia.org/property/countryOfProduction", "http://dbpedia.org/property/foundedDate", "http://dbpedia.org/ontology/place", "http://dbpedia.org/property/operatingAgency", "http://dbpedia.org/property/nearestCity", "http://purl.org/dc/terms/subject", "http://dbpedia.org/ontology/populationPlace", "http://dbpedia.org/ontology/commandStructure", "http://dbpedia.org/property/countryAdminDivisions", "http://dbpedia.org/property/state", "http://dbpedia.org/property/sections", "http://dbpedia.org/property/returns", "http://dbpedia.org/property/cityServed", "http://dbpedia.org/ontology/headquarter", "http://dbpedia.org/property/foundation", "http://dbpedia.org/ontology/region", "http://dbpedia.org/property/data", "http://dbpedia.org/ontology/sourceCountry", "http://dbpedia.org/ontology/broadcastArea", "http://dbpedia.org/property/studio", "http://dbpedia.org/ontology/residence", "http://dbpedia.org/ontology/timeZone", "http://dbpedia.org/property/shipHomeport", "http://dbpedia.org/property/regionServed", "http://dbpedia.org/property/locationCity", "http://dbpedia.org/ontology/locationCity"]]}}, "sparql_template_id": 305, "entity": ["http://dbpedia.org/resource/Hawaii"], "path": ["-http://dbpedia.org/property/college", "+http://dbpedia.org/ontology/debutTeam"], "_id": "e4f65c146f2447c0b3c8147f59a837e1", "constraints": {"?x": "http://www.w3.org/1999/02/22-rdf-syntax-ns#type"}}, {"verbalized_question": "What is the <city> of the <rivers> whose <right tributary> is <Big Spring (Missouri)>?", "corrected_question": "Which cities have the river one of whose Tributary is the Missouri's big spring?", "sparql_query": "SELECT DISTINCT ?uri WHERE { ?x <http://dbpedia.org/ontology/rightTributary> <http://dbpedia.org/resource/Big_Spring_(Missouri)> . ?x <http://dbpedia.org/ontology/city> ?uri  . ?x <http://www.w3.org/1999/02/22-rdf-syntax-ns#type> <http://dbpedia.org/ontology/River>}", "training": {"http://dbpedia.org/resource/Big_Spring_(Missouri)": {"rel2": [[{"http://dbpedia.org/ontology/mouthMountain": [["http://dbpedia.org/property/elevationM", "http://dbpedia.org/ontology/elevation", "http://dbpedia.org/property/areaWaterKm", "http://dbpedia.org/property/elevationFt", "http://dbpedia.org/property/areaWaterSqMi"], ["http://dbpedia.org/ontology/mouthMountain", "http://dbpedia.org/ontology/mouthPlace"]]}, {"http://dbpedia.org/property/mouthElevationImperial": [[], []]}], [{"http://dbpedia.org/property/city": [["http://dbpedia.org/property/county", "http://dbpedia.org/property/city"], ["http://xmlns.com/foaf/0.1/primaryTopic", "http://dbpedia.org/ontology/wikiPageWikiLink", "http://dbpedia.org/ontology/wikiPageRedirects"]]}, {"http://dbpedia.org/property/tributaryRight": [["http://dbpedia.org/property/tributaryRight", "http://dbpedia.org/ontology/rightTributary"], ["http://xmlns.com/foaf/0.1/primaryTopic", "http://dbpedia.org/ontology/wikiPageDisambiguates", "http://dbpedia.org/ontology/wikiPageWikiLink", "http://dbpedia.org/ontology/wikiPageRedirects"]]}, {"http://dbpedia.org/ontology/wikiPageWikiLink": [["http://dbpedia.org/ontology/wikiPageExternalLink", "http://dbpedia.org/ontology/wikiPageWikiLink"], ["http://dbpedia.org/ontology/wikiPageRedirects", "http://dbpedia.org/ontology/sourcePlace", "http://dbpedia.org/property/isCitedBy", "http://dbpedia.org/ontology/wikiPageWikiLink", "http://dbpedia.org/ontology/routeStart"]]}, {"http://dbpedia.org/ontology/rightTributary": [["http://dbpedia.org/property/tributaryRight", "http://dbpedia.org/ontology/rightTributary"], ["http://xmlns.com/foaf/0.1/primaryTopic", "http://dbpedia.org/ontology/wikiPageDisambiguates", "http://dbpedia.org/ontology/wikiPageWikiLink", "http://dbpedia.org/ontology/wikiPageRedirects"]]}, {"http://dbpedia.org/ontology/wikiPageRedirects": [["http://dbpedia.org/ontology/wikiPageRedirects", "http://dbpedia.org/ontology/wikiPageWikiLink"], ["http://xmlns.com/foaf/0.1/primaryTopic"]]}]], "rel1": [["http://dbpedia.org/ontology/mouthElevation", "http://dbpedia.org/ontology/discharge", "http://dbpedia.org/ontology/mouthRegion", "http://dbpedia.org/property/imageCaption", "http://dbpedia.org/ontology/minimumDischarge", "http://dbpedia.org/ontology/wikiPageWikiLink", "http://dbpedia.org/ontology/Stream/minimumDischarge", "http://dbpedia.org/property/sourceCoordinatesNote", "http://dbpedia.org/property/mouthName", "http://dbpedia.org/property/mouthState", "http://dbpedia.org/property/dischargeMinImperial", "http://www.w3.org/ns/prov#wasDerivedFrom", "http://purl.org/dc/terms/subject", "http://dbpedia.org/ontology/length", "http://dbpedia.org/property/sourceName", "http://dbpedia.org/ontology/country", "http://dbpedia.org/property/region", "http://dbpedia.org/property/wikiPageUsesTemplate", "http://dbpedia.org/property/mouthLatM", "http://dbpedia.org/property/mouthElevationImperial", "http://www.w3.org/2000/01/rdf-schema#label", "http://dbpedia.org/property/mouthLongD", "http://dbpedia.org/property/mouthLatD", "http://dbpedia.org/property/dischargeImperial", "http://dbpedia.org/property/mouthRegion", "http://dbpedia.org/property/sourceElevationNote", "http://xmlns.com/foaf/0.1/isPrimaryTopicOf", "http://dbpedia.org/property/mouthLocation", "http://dbpedia.org/property/mouthLatS", "http://dbpedia.org/property/state", "http://dbpedia.org/property/mouthCoordinatesNote", "http://dbpedia.org/ontology/wikiPageExternalLink", "http://dbpedia.org/property/dischargeMaxImperial", "http://dbpedia.org/property/mouthLongS", "http://dbpedia.org/ontology/Stream/maximumDischarge", "http://dbpedia.org/property/mouthLongEw", "http://dbpedia.org/ontology/abstract", "http://xmlns.com/foaf/0.1/depiction", "http://dbpedia.org/ontology/wikiPageID", "http://dbpedia.org/property/mouthDistrict", "http://dbpedia.org/ontology/mouthMountain", "http://www.w3.org/1999/02/22-rdf-syntax-ns#type", "http://dbpedia.org/ontology/thumbnail", "http://dbpedia.org/ontology/maximumDischarge", "http://dbpedia.org/property/country", "http://dbpedia.org/property/sourceState", "http://dbpedia.org/ontology/region", "http://dbpedia.org/ontology/mouthPlace", "http://dbpedia.org/ontology/state", "http://dbpedia.org/property/sourceRegion", "http://dbpedia.org/property/sourceDistrict", "http://www.w3.org/2000/01/rdf-schema#comment", "http://dbpedia.org/ontology/wikiPageWikiLinkText", "http://dbpedia.org/property/lengthImperial", "http://dbpedia.org/property/name", "http://dbpedia.org/ontology/wikiPageOutDegree", "http://dbpedia.org/property/imageSize", "http://dbpedia.org/property/mouthElevationNote", "http://dbpedia.org/ontology/wikiPageLength", "http://dbpedia.org/property/mouthLatNs", "http://dbpedia.org/property/dischargeLocation", "http://dbpedia.org/ontology/Stream/discharge", "http://dbpedia.org/ontology/wikiPageRevisionID", "http://xmlns.com/foaf/0.1/name", "http://dbpedia.org/ontology/sourceRegion", "http://dbpedia.org/property/mouthLongM", "http://dbpedia.org/ontology/mouthPosition", "http://www.w3.org/2002/07/owl#sameAs"], ["http://xmlns.com/foaf/0.1/primaryTopic", "http://dbpedia.org/property/isCitedBy", "http://dbpedia.org/property/tributaryRight", "http://dbpedia.org/ontology/wikiPageWikiLink", "http://dbpedia.org/ontology/wikiPageRedirects", "http://dbpedia.org/property/city", "http://dbpedia.org/ontology/wikiPageDisambiguates", "http://dbpedia.org/ontology/rightTributary"]]}}, "sparql_template_id": 305, "entity": ["http://dbpedia.org/resource/Big_Spring_(Missouri)"], "path": ["-http://dbpedia.org/ontology/rightTributary", "+http://dbpedia.org/ontology/city"], "_id": "1c6538227a4d41fdbcdb11eda17bce21", "constraints": {"?x": "http://www.w3.org/1999/02/22-rdf-syntax-ns#type"}}, {"verbalized_question": "What is the <writer> of the <owls> whose <magazine> is <Gangan Comics>?", "corrected_question": "Who has written works found in the Gangan comics?", "sparql_query": "SELECT DISTINCT ?uri WHERE { ?x <http://dbpedia.org/property/magazine> <http://dbpedia.org/resource/Gangan_Comics> . ?x <http://dbpedia.org/property/author> ?uri  . }", "training": {"http://dbpedia.org/resource/Gangan_Comics": {"rel2": [[{"http://dbpedia.org/property/website": [[], []]}, {"http://dbpedia.org/ontology/publisher": [["http://dbpedia.org/ontology/wikiPageID", "http://dbpedia.org/ontology/subsidiary", "http://dbpedia.org/ontology/wikiPageLength", "http://dbpedia.org/property/subsid", "http://dbpedia.org/ontology/wikiPageOutDegree"], ["http://dbpedia.org/ontology/publisher", "http://dbpedia.org/property/publisher"]]}], [{"http://dbpedia.org/property/imprint": [["http://dbpedia.org/property/imprint", "http://dbpedia.org/property/label"], ["http://www.w3.org/2000/01/rdf-schema#seeAlso", "http://dbpedia.org/property/isCitedBy", "http://dbpedia.org/ontology/wikiPageDisambiguates", "http://dbpedia.org/ontology/wikiPageRedirects", "http://dbpedia.org/ontology/wikiPageWikiLink"]]}, {"http://dbpedia.org/ontology/publisher": [["http://dbpedia.org/ontology/publisher", "http://dbpedia.org/property/publisher"], ["http://xmlns.com/foaf/0.1/primaryTopic", "http://dbpedia.org/ontology/wikiPageRedirects", "http://dbpedia.org/property/isCitedBy", "http://dbpedia.org/ontology/knownFor", "http://dbpedia.org/ontology/wikiPageWikiLink"]]}, {"http://dbpedia.org/property/magazine": [["http://dbpedia.org/property/magazine", "http://dbpedia.org/ontology/magazine"], ["http://dbpedia.org/property/products", "http://dbpedia.org/property/series", "http://dbpedia.org/ontology/illustrator", "http://dbpedia.org/property/isCitedBy", "http://dbpedia.org/ontology/series"]]}, {"http://dbpedia.org/ontology/magazine": [["http://dbpedia.org/property/magazine", "http://dbpedia.org/ontology/magazine"], ["http://dbpedia.org/property/products", "http://dbpedia.org/property/series", "http://dbpedia.org/ontology/illustrator", "http://dbpedia.org/property/isCitedBy", "http://dbpedia.org/ontology/series"]]}, {"http://dbpedia.org/property/publisher": [["http://dbpedia.org/ontology/publisher", "http://dbpedia.org/property/publisher"], ["http://xmlns.com/foaf/0.1/primaryTopic", "http://dbpedia.org/ontology/wikiPageRedirects", "http://dbpedia.org/property/isCitedBy", "http://dbpedia.org/ontology/knownFor", "http://dbpedia.org/ontology/wikiPageWikiLink"]]}]], "rel1": [["http://dbpedia.org/property/website", "http://dbpedia.org/ontology/date", "http://dbpedia.org/property/imageCaption", "http://dbpedia.org/ontology/wikiPageWikiLinkText", "http://www.w3.org/ns/prov#wasDerivedFrom", "http://dbpedia.org/ontology/publisher", "http://www.w3.org/1999/02/22-rdf-syntax-ns#type", "http://dbpedia.org/property/category", "http://purl.org/linguistics/gold/hypernym", "http://dbpedia.org/property/imageFile", "http://xmlns.com/foaf/0.1/isPrimaryTopicOf", "http://dbpedia.org/property/language", "http://dbpedia.org/property/country", "http://dbpedia.org/property/wordnet_type", "http://dbpedia.org/ontology/wikiPageExternalLink", "http://dbpedia.org/ontology/depictionDescription", "http://purl.org/dc/terms/subject", "http://dbpedia.org/property/firstdate", "http://dbpedia.org/ontology/abstract", "http://dbpedia.org/ontology/wikiPageID", "http://dbpedia.org/property/company", "http://dbpedia.org/property/wikiPageUsesTemplate", "http://www.w3.org/2000/01/rdf-schema#label", "http://dbpedia.org/ontology/language", "http://dbpedia.org/property/title", "http://dbpedia.org/ontology/genre", "http://www.w3.org/2000/01/rdf-schema#comment", "http://dbpedia.org/property/frequency", "http://dbpedia.org/ontology/wikiPageWikiLink", "http://dbpedia.org/ontology/wikiPageOutDegree", "http://dbpedia.org/ontology/wikiPageLength", "http://dbpedia.org/ontology/imageSize", "http://xmlns.com/foaf/0.1/name", "http://xmlns.com/foaf/0.1/homepage", "http://dbpedia.org/ontology/wikiPageRevisionID", "http://dbpedia.org/property/imageSize", "http://www.w3.org/2002/07/owl#sameAs"], ["http://dbpedia.org/ontology/publisher", "http://xmlns.com/foaf/0.1/primaryTopic", "http://dbpedia.org/property/isCitedBy", "http://dbpedia.org/property/magazine", "http://dbpedia.org/ontology/wikiPageWikiLink", "http://dbpedia.org/ontology/wikiPageRedirects", "http://dbpedia.org/ontology/magazine", "http://dbpedia.org/property/work", "http://dbpedia.org/property/imprint", "http://dbpedia.org/property/publisher", "http://dbpedia.org/ontology/wikiPageDisambiguates"]]}}, "sparql_template_id": 5, "entity": ["http://dbpedia.org/resource/Gangan_Comics"], "path": ["-http://dbpedia.org/property/magazine", "+http://dbpedia.org/property/author"], "_id": "a45050c81a4d44f28d5f4050ae9db959", "constraints": {}}, {"verbalized_question": "What is the <currency> of Republic of Montenegro (19922006) ?", "corrected_question": "What is the currency of Republic of Montenegro (1992-2006) ?", "sparql_query": " SELECT DISTINCT ?uri WHERE { <http://dbpedia.org/resource/Republic_of_Montenegro_(1992\u20132006)> <http://dbpedia.org/property/currency> ?uri } ", "training": {"http://dbpedia.org/resource/Republic_of_Montenegro_(1992\u20132006)": {"rel1": [["http://dbpedia.org/property/currency", "http://dbpedia.org/property/flag", "http://dbpedia.org/property/governmentType", "http://dbpedia.org/property/deputy", "http://dbpedia.org/property/conventionalLongName", "http://dbpedia.org/ontology/wikiPageWikiLinkText", "http://dbpedia.org/property/continent", "http://dbpedia.org/property/statArea", "http://www.w3.org/ns/prov#wasDerivedFrom", "http://dbpedia.org/property/yearLeader", "http://dbpedia.org/property/flagS", "http://dbpedia.org/property/dateEvent", "http://dbpedia.org/property/symbolType", "http://dbpedia.org/property/flagP", "http://dbpedia.org/property/legislature", "http://dbpedia.org/property/dateStart", "http://dbpedia.org/property/leader", "http://dbpedia.org/property/nation", "http://dbpedia.org/property/p", "http://dbpedia.org/property/region", "http://dbpedia.org/property/nationalAnthem", "http://dbpedia.org/property/subdivision", "http://dbpedia.org/property/eventEnd", "http://dbpedia.org/property/dateEnd", "http://purl.org/linguistics/gold/hypernym", "http://dbpedia.org/property/event", "http://www.w3.org/1999/02/22-rdf-syntax-ns#type", "http://dbpedia.org/property/capital", "http://dbpedia.org/property/commonName", "http://xmlns.com/foaf/0.1/isPrimaryTopicOf", "http://dbpedia.org/ontology/currency", "http://dbpedia.org/property/nativeName", "http://dbpedia.org/property/imageMapCaption", "http://dbpedia.org/property/symbol", "http://dbpedia.org/property/yearEnd", "http://purl.org/dc/terms/subject", "http://dbpedia.org/property/religion", "http://dbpedia.org/ontology/abstract", "http://xmlns.com/foaf/0.1/depiction", "http://dbpedia.org/ontology/wikiPageID", "http://dbpedia.org/property/s", "http://dbpedia.org/property/commonLanguages", "http://xmlns.com/foaf/0.1/name", "http://dbpedia.org/property/wikiPageUsesTemplate", "http://dbpedia.org/ontology/thumbnail", "http://dbpedia.org/property/yearStart", "http://www.w3.org/2000/01/rdf-schema#label", "http://dbpedia.org/property/eventStart", "http://dbpedia.org/property/imageMap", "http://www.w3.org/2000/01/rdf-schema#comment", "http://dbpedia.org/ontology/anthem", "http://dbpedia.org/ontology/capital", "http://dbpedia.org/ontology/wikiPageWikiLink", "http://dbpedia.org/ontology/wikiPageOutDegree", "http://dbpedia.org/property/yearDeputy", "http://dbpedia.org/ontology/wikiPageLength", "http://dbpedia.org/property/titleLeader", "http://dbpedia.org/property/imageFlag", "http://dbpedia.org/property/flagType", "http://dbpedia.org/property/imageCoat", "http://dbpedia.org/property/titleDeputy", "http://dbpedia.org/ontology/wikiPageRevisionID", "http://www.w3.org/2002/07/owl#sameAs", "http://dbpedia.org/property/statYear"], ["http://xmlns.com/foaf/0.1/primaryTopic", "http://dbpedia.org/property/isCitedBy", "http://dbpedia.org/ontology/currency", "http://dbpedia.org/ontology/birthPlace", "http://dbpedia.org/property/deathPlace", "http://dbpedia.org/ontology/wikiPageRedirects", "http://dbpedia.org/property/location", "http://dbpedia.org/ontology/deathPlace", "http://dbpedia.org/ontology/wikiPageWikiLink", "http://dbpedia.org/ontology/wikiPageDisambiguates", "http://www.w3.org/2002/07/owl#sameAs"]]}}, "sparql_template_id": 2, "entity": ["http://dbpedia.org/resource/Republic_of_Montenegro_(1992\u20132006)"], "path": ["+http://dbpedia.org/property/currency"], "_id": "3cade710572444c297c339d6443854ed", "constraints": {}}, {"verbalized_question": "What is the <Guests> of the <television episodes> whose <music> is <Mama  Makes  Three>>?", "corrected_question": "Who has given guest appearances on the TV Episodes whose was music done by Mama Makes 3?", "sparql_query": "SELECT DISTINCT ?uri WHERE { ?x <http://dbpedia.org/property/music> <http://dbpedia.org/resource/Mama_Makes_Three> . ?x <http://dbpedia.org/property/guests> ?uri  . ?x <http://www.w3.org/1999/02/22-rdf-syntax-ns#type> <http://dbpedia.org/ontology/TelevisionEpisode>}", "training": {"http://dbpedia.org/resource/Mama_Makes_Three": {"rel2": [[{"http://www.w3.org/1999/02/22-rdf-syntax-ns#type": [[], []]}, {"http://dbpedia.org/ontology/wikiPageWikiLinkText": [[], []]}], [{"http://dbpedia.org/ontology/musicComposer": [["http://dbpedia.org/ontology/musicComposer", "http://dbpedia.org/property/music"], ["http://xmlns.com/foaf/0.1/primaryTopic", "http://dbpedia.org/ontology/subsequentWork", "http://dbpedia.org/ontology/previousWork", "http://dbpedia.org/ontology/wikiPageWikiLink", "http://dbpedia.org/property/next"]]}, {"http://dbpedia.org/property/music": [["http://dbpedia.org/ontology/musicComposer", "http://dbpedia.org/property/music"], ["http://xmlns.com/foaf/0.1/primaryTopic", "http://dbpedia.org/ontology/subsequentWork", "http://dbpedia.org/ontology/previousWork", "http://dbpedia.org/ontology/wikiPageWikiLink", "http://dbpedia.org/property/next"]]}, {"http://dbpedia.org/ontology/wikiPageWikiLink": [["http://dbpedia.org/ontology/wikiPageExternalLink", "http://dbpedia.org/ontology/wikiPageWikiLink"], ["http://xmlns.com/foaf/0.1/primaryTopic", "http://dbpedia.org/ontology/subsequentWork", "http://dbpedia.org/ontology/previousWork", "http://dbpedia.org/ontology/wikiPageWikiLink", "http://dbpedia.org/property/next"]]}]], "rel1": [["http://www.w3.org/1999/02/22-rdf-syntax-ns#type", "http://dbpedia.org/ontology/wikiPageWikiLinkText"], ["http://dbpedia.org/ontology/musicComposer", "http://dbpedia.org/property/music", "http://dbpedia.org/ontology/wikiPageWikiLink"]]}}, "sparql_template_id": 305, "entity": ["http://dbpedia.org/resource/Mama_Makes_Three"], "path": ["-http://dbpedia.org/property/music", "+http://dbpedia.org/property/guests"], "_id": "0c03e9d597b44f8bbef68457b98bb7c1", "constraints": {"?x": "http://www.w3.org/1999/02/22-rdf-syntax-ns#type"}}, {"verbalized_question": "What is the <Band> whose <former band member> is <Kevin Jonas>?", "corrected_question": "Which band was left by Kevin Jonas?", "sparql_query": "SELECT DISTINCT ?uri WHERE {?uri <http://dbpedia.org/ontology/formerBandMember> <http://dbpedia.org/resource/Kevin_Jonas>  . ?uri <http://www.w3.org/1999/02/22-rdf-syntax-ns#type> <http://dbpedia.org/ontology/Band>}", "training": {"http://dbpedia.org/resource/Kevin_Jonas": {"rel1": [["http://dbpedia.org/property/birthDate", "http://dbpedia.org/ontology/wikiPageWikiLinkText", "http://dbpedia.org/property/name", "http://dbpedia.org/property/occupation", "http://www.w3.org/ns/prov#wasDerivedFrom", "http://dbpedia.org/property/caption", "http://dbpedia.org/property/spouse", "http://dbpedia.org/property/children", "http://dbpedia.org/property/dateOfBirth", "http://www.w3.org/1999/02/22-rdf-syntax-ns#type", "http://purl.org/linguistics/gold/hypernym", "http://dbpedia.org/property/alias", "http://dbpedia.org/ontology/birthName", "http://dbpedia.org/property/wordnet_type", "http://dbpedia.org/property/birthPlace", "http://dbpedia.org/property/shortDescription", "http://dbpedia.org/property/placeOfBirth", "http://dbpedia.org/property/birthName", "http://xmlns.com/foaf/0.1/isPrimaryTopicOf", "http://purl.org/dc/terms/subject", "http://purl.org/dc/elements/1.1/description", "http://dbpedia.org/ontology/abstract", "http://xmlns.com/foaf/0.1/depiction", "http://dbpedia.org/ontology/wikiPageID", "http://dbpedia.org/property/wikiPageUsesTemplate", "http://dbpedia.org/ontology/thumbnail", "http://dbpedia.org/ontology/birthYear", "http://www.w3.org/2000/01/rdf-schema#label", "http://dbpedia.org/ontology/birthDate", "http://xmlns.com/foaf/0.1/givenName", "http://www.w3.org/2000/01/rdf-schema#comment", "http://dbpedia.org/ontology/birthPlace", "http://xmlns.com/foaf/0.1/surname", "http://dbpedia.org/ontology/wikiPageWikiLink", "http://dbpedia.org/ontology/wikiPageOutDegree", "http://dbpedia.org/ontology/wikiPageLength", "http://xmlns.com/foaf/0.1/name", "http://dbpedia.org/ontology/wikiPageRevisionID", "http://www.w3.org/2002/07/owl#sameAs", "http://dbpedia.org/ontology/occupation"], ["http://xmlns.com/foaf/0.1/primaryTopic", "http://dbpedia.org/ontology/starring", "http://dbpedia.org/property/pastMembers", "http://dbpedia.org/ontology/formerBandMember", "http://dbpedia.org/ontology/wikiPageWikiLink", "http://dbpedia.org/ontology/wikiPageRedirects", "http://dbpedia.org/ontology/writer", "http://dbpedia.org/property/writer", "http://dbpedia.org/property/starring", "http://dbpedia.org/property/isCitedBy"]]}}, "sparql_template_id": 301, "entity": ["http://dbpedia.org/resource/Kevin_Jonas"], "path": ["-http://dbpedia.org/ontology/formerBandMember"], "_id": "9cda2b2237914ed59d7fe4aae8bc2c1d", "constraints": {"?uri": "http://www.w3.org/1999/02/22-rdf-syntax-ns#type"}}, {"verbalized_question": "What is the <national origin> of the <aircraft> whose <built by> is <Start +  Flug>> ?", "corrected_question": "In which countries have the Start + Flug aircrafts originated?", "sparql_query": "SELECT DISTINCT ?uri WHERE { ?x <http://dbpedia.org/ontology/manufacturer> <http://dbpedia.org/resource/Start_+_Flug> . ?x <http://dbpedia.org/property/nationalOrigin> ?uri  . ?x <http://www.w3.org/1999/02/22-rdf-syntax-ns#type> <http://dbpedia.org/ontology/Aircraft>}", "training": {"http://dbpedia.org/resource/Start_+_Flug": {"rel2": [[{"http://www.w3.org/1999/02/22-rdf-syntax-ns#type": [[], []]}, {"http://dbpedia.org/ontology/wikiPageWikiLinkText": [[], []]}], [{"http://dbpedia.org/ontology/manufacturer": [["http://xmlns.com/foaf/0.1/name", "http://dbpedia.org/property/manufacturer"], ["http://xmlns.com/foaf/0.1/primaryTopic", "http://dbpedia.org/ontology/wikiPageRedirects", "http://dbpedia.org/ontology/wikiPageWikiLink", "http://dbpedia.org/property/isCitedBy"]]}, {"http://dbpedia.org/ontology/wikiPageWikiLink": [["http://dbpedia.org/ontology/wikiPageExternalLink", "http://dbpedia.org/ontology/wikiPageWikiLink"], ["http://dbpedia.org/ontology/wikiPageRedirects", "http://dbpedia.org/property/isCitedBy", "http://dbpedia.org/ontology/wikiPageWikiLink", "http://dbpedia.org/property/lists", "http://dbpedia.org/property/seeAlso"]]}, {"http://dbpedia.org/property/manufacturer": [["http://dbpedia.org/property/numberBuilt", "http://dbpedia.org/property/manufacturer"], ["http://xmlns.com/foaf/0.1/primaryTopic", "http://dbpedia.org/ontology/wikiPageRedirects", "http://dbpedia.org/property/isCitedBy", "http://dbpedia.org/ontology/wikiPageWikiLink"]]}]], "rel1": [["http://www.w3.org/1999/02/22-rdf-syntax-ns#type", "http://dbpedia.org/ontology/wikiPageWikiLinkText"], ["http://dbpedia.org/property/manufacturer", "http://dbpedia.org/ontology/wikiPageWikiLink", "http://dbpedia.org/ontology/manufacturer"]]}}, "sparql_template_id": 305, "entity": ["http://dbpedia.org/resource/Start_+_Flug"], "path": ["-http://dbpedia.org/ontology/manufacturer", "+http://dbpedia.org/property/nationalOrigin"], "_id": "9f314843488844988113ecbbe314006d", "constraints": {"?x": "http://www.w3.org/1999/02/22-rdf-syntax-ns#type"}}, {"verbalized_question": "Who are the <basketball players> whose <sports league> is <National Basketball Association>?", "corrected_question": "return some  players who have played in the NBA?", "sparql_query": " SELECT DISTINCT ?uri WHERE {?uri <http://dbpedia.org/property/league> <http://dbpedia.org/resource/National_Basketball_Association> } ", "training": {"http://dbpedia.org/resource/National_Basketball_Association": {"rel1": [["http://www.w3.org/2000/01/rdf-schema#seeAlso", "http://dbpedia.org/ontology/wikiPageExternalLink", "http://dbpedia.org/property/mostChamps", "http://dbpedia.org/ontology/wikiPageWikiLinkText", "http://dbpedia.org/property/continent", "http://dbpedia.org/property/pixels", "http://www.w3.org/ns/prov#wasDerivedFrom", "http://purl.org/dc/terms/subject", "http://www.w3.org/1999/02/22-rdf-syntax-ns#type", "http://purl.org/linguistics/gold/hypernym", "http://dbpedia.org/property/teams", "http://dbpedia.org/property/wordnet_type", "http://xmlns.com/foaf/0.1/isPrimaryTopicOf", "http://dbpedia.org/ontology/abstract", "http://dbpedia.org/property/tv", "http://dbpedia.org/ontology/foundingYear", "http://dbpedia.org/ontology/formationDate", "http://dbpedia.org/ontology/currentSeason", "http://dbpedia.org/property/commissioner", "http://xmlns.com/foaf/0.1/depiction", "http://dbpedia.org/ontology/wikiPageID", "http://dbpedia.org/property/sport", "http://dbpedia.org/property/logo", "http://dbpedia.org/property/wikiPageUsesTemplate", "http://dbpedia.org/ontology/thumbnail", "http://www.w3.org/2000/01/rdf-schema#label", "http://dbpedia.org/property/inaugural", "http://dbpedia.org/property/title", "http://dbpedia.org/property/currentSeason", "http://dbpedia.org/property/countries", "http://www.w3.org/2000/01/rdf-schema#comment", "http://dbpedia.org/ontology/wikiPageWikiLink", "http://dbpedia.org/ontology/wikiPageOutDegree", "http://dbpedia.org/property/champion", "http://dbpedia.org/ontology/wikiPageLength", "http://dbpedia.org/ontology/title", "http://dbpedia.org/property/founded", "http://xmlns.com/foaf/0.1/homepage", "http://dbpedia.org/ontology/wikiPageRevisionID", "http://dbpedia.org/ontology/participant", "http://www.w3.org/2002/07/owl#sameAs"], ["http://www.w3.org/2000/01/rdf-schema#seeAlso", "http://dbpedia.org/property/affiliation", "http://dbpedia.org/ontology/associatedMusicalArtist", "http://dbpedia.org/property/accredetation", "http://dbpedia.org/property/isCitedBy", "http://dbpedia.org/property/presenter", "http://dbpedia.org/ontology/team", "http://dbpedia.org/property/nota", "http://dbpedia.org/ontology/wikiPageRedirects", "http://dbpedia.org/ontology/owningCompany", "http://dbpedia.org/property/league", "http://dbpedia.org/ontology/knownFor", "http://dbpedia.org/property/occupation", "http://dbpedia.org/property/genre", "http://www.w3.org/2002/07/owl#differentFrom", "http://dbpedia.org/ontology/format", "http://dbpedia.org/property/conference", "http://dbpedia.org/property/field", "http://dbpedia.org/property/website", "http://dbpedia.org/property/affiliations", "http://dbpedia.org/property/work", "http://dbpedia.org/property/employer", "http://dbpedia.org/property/owner", "http://dbpedia.org/ontology/affiliation", "http://dbpedia.org/ontology/wikiPageDisambiguates", "http://dbpedia.org/ontology/broadcastNetwork", "http://xmlns.com/foaf/0.1/primaryTopic", "http://purl.org/dc/terms/subject", "http://dbpedia.org/property/organization", "http://dbpedia.org/ontology/league", "http://dbpedia.org/property/organized", "http://dbpedia.org/property/body", "http://dbpedia.org/property/format", "http://dbpedia.org/property/publisher", "http://dbpedia.org/ontology/programmeFormat", "http://dbpedia.org/ontology/tenant", "http://dbpedia.org/ontology/genre", "http://dbpedia.org/ontology/presenter", "http://dbpedia.org/property/sport", "http://dbpedia.org/ontology/wikiPageWikiLink", "http://dbpedia.org/property/relatedComps", "http://dbpedia.org/ontology/owner", "http://dbpedia.org/property/seatingCapacity", "http://dbpedia.org/ontology/field", "http://dbpedia.org/ontology/employer", "http://dbpedia.org/ontology/associatedBand", "http://dbpedia.org/ontology/occupation"]]}}, "sparql_template_id": 1, "entity": ["http://dbpedia.org/resource/National_Basketball_Association"], "path": ["-http://dbpedia.org/property/league"], "_id": "1979785c219b4798a0610b3ffc06873b", "constraints": {}}, {"verbalized_question": "What is the <nearest city> of Tennie and Laura (schooner) ?", "corrected_question": "Name the nearest city to Tennie and Laura ?", "sparql_query": " SELECT DISTINCT ?uri WHERE { <http://dbpedia.org/resource/Tennie_and_Laura_(schooner)> <http://dbpedia.org/property/nearestCity> ?uri } ", "training": {"http://dbpedia.org/resource/Tennie_and_Laura_(schooner)": {"rel1": [["http://dbpedia.org/property/added", "http://dbpedia.org/ontology/wikiPageWikiLinkText", "http://dbpedia.org/property/name", "http://dbpedia.org/property/shipLength", "http://dbpedia.org/property/shipName", "http://dbpedia.org/property/shipFate", "http://dbpedia.org/property/shipCrew", "http://www.w3.org/ns/prov#wasDerivedFrom", "http://dbpedia.org/property/shipFlag", "http://www.w3.org/1999/02/22-rdf-syntax-ns#type", "http://dbpedia.org/property/shipNotes", "http://purl.org/linguistics/gold/hypernym", "http://dbpedia.org/ontology/MeanOfTransportation/length", "http://dbpedia.org/property/shipTonnage", "http://xmlns.com/foaf/0.1/isPrimaryTopicOf", "http://dbpedia.org/property/shipCountry", "http://dbpedia.org/property/nearestCity", "http://dbpedia.org/ontology/height", "http://purl.org/dc/terms/subject", "http://dbpedia.org/property/shipBeam", "http://dbpedia.org/ontology/abstract", "http://xmlns.com/foaf/0.1/depiction", "http://dbpedia.org/ontology/wikiPageID", "http://dbpedia.org/property/location", "http://dbpedia.org/ontology/shipBeam", "http://dbpedia.org/property/wikiPageUsesTemplate", "http://dbpedia.org/ontology/thumbnail", "http://dbpedia.org/ontology/length", "http://www.w3.org/2000/01/rdf-schema#label", "http://dbpedia.org/property/nrhpType", "http://dbpedia.org/property/shipCompleted", "http://dbpedia.org/property/shipBuilder", "http://www.w3.org/2000/01/rdf-schema#comment", "http://dbpedia.org/ontology/status", "http://dbpedia.org/property/shipOperator", "http://dbpedia.org/property/shipClass", "http://dbpedia.org/ontology/wikiPageWikiLink", "http://dbpedia.org/ontology/wikiPageOutDegree", "http://dbpedia.org/ontology/wikiPageLength", "http://dbpedia.org/ontology/MeanOfTransportation/height", "http://www.w3.org/2002/07/owl#sameAs", "http://dbpedia.org/property/refnum", "http://xmlns.com/foaf/0.1/name", "http://dbpedia.org/property/shipHeight", "http://dbpedia.org/ontology/wikiPageRevisionID", "http://dbpedia.org/property/shipStatus"], ["http://xmlns.com/foaf/0.1/primaryTopic", "http://dbpedia.org/ontology/wikiPageRedirects", "http://dbpedia.org/ontology/wikiPageWikiLink"]]}}, "sparql_template_id": 2, "entity": ["http://dbpedia.org/resource/Tennie_and_Laura_(schooner)"], "path": ["+http://dbpedia.org/property/nearestCity"], "_id": "dc586a5d041844feb7a1d08718b05042", "constraints": {}}, {"verbalized_question": "What is the <Home Stadium> of Kenya national under-20 football team ?", "corrected_question": "Name the home Stadium of Kenya national under-20 football team ?", "sparql_query": " SELECT DISTINCT ?uri WHERE { <http://dbpedia.org/resource/Kenya_national_under-20_football_team> <http://dbpedia.org/property/homeStadium> ?uri } ", "training": {"http://dbpedia.org/resource/Kenya_national_under-20_football_team": {"rel1": [["http://dbpedia.org/property/association", "http://dbpedia.org/ontology/wikiPageWikiLinkText", "http://dbpedia.org/property/homeStadium", "http://dbpedia.org/property/name", "http://dbpedia.org/property/regionalName", "http://dbpedia.org/property/confederation", "http://www.w3.org/ns/prov#wasDerivedFrom", "http://dbpedia.org/property/subConfederation", "http://dbpedia.org/property/nickname", "http://www.w3.org/1999/02/22-rdf-syntax-ns#type", "http://dbpedia.org/property/patternB", "http://dbpedia.org/property/socks", "http://xmlns.com/foaf/0.1/isPrimaryTopicOf", "http://dbpedia.org/property/body", "http://xmlns.com/foaf/0.1/nick", "http://purl.org/dc/terms/subject", "http://dbpedia.org/property/shorts", "http://dbpedia.org/property/leftarm", "http://dbpedia.org/ontology/abstract", "http://dbpedia.org/ontology/wikiPageID", "http://dbpedia.org/property/wikiPageUsesTemplate", "http://dbpedia.org/ontology/stadium", "http://dbpedia.org/property/fifaTrigramme", "http://dbpedia.org/property/patternSh", "http://www.w3.org/2000/01/rdf-schema#label", "http://www.w3.org/2000/01/rdf-schema#comment", "http://dbpedia.org/ontology/wikiPageWikiLink", "http://dbpedia.org/ontology/wikiPageOutDegree", "http://dbpedia.org/ontology/wikiPageLength", "http://xmlns.com/foaf/0.1/name", "http://dbpedia.org/ontology/wikiPageRevisionID", "http://dbpedia.org/property/rightarm", "http://www.w3.org/2002/07/owl#sameAs"], ["http://dbpedia.org/property/nationalteam", "http://xmlns.com/foaf/0.1/primaryTopic", "http://dbpedia.org/ontology/wikiPageRedirects", "http://dbpedia.org/ontology/wikiPageWikiLink"]]}}, "sparql_template_id": 2, "entity": ["http://dbpedia.org/resource/Kenya_national_under-20_football_team"], "path": ["+http://dbpedia.org/property/homeStadium"], "_id": "a5e0d47ce7c24a0ea619a0edcaad11e8", "constraints": {}}, {"verbalized_question": "What is the <resting place> of the <politician> who is the <successor> of <Samuel Hayes (settler)> ?", "corrected_question": "What is the resting place of the politician who succeeded Samuel Hayes?", "sparql_query": "SELECT DISTINCT ?uri WHERE { <http://dbpedia.org/resource/Samuel_Hayes_(settler)> <http://dbpedia.org/ontology/successor> ?x . ?x <http://dbpedia.org/ontology/restingPlace> ?uri  . ?x <http://www.w3.org/1999/02/22-rdf-syntax-ns#type> <http://dbpedia.org/ontology/Politician>}", "training": {"http://dbpedia.org/resource/Samuel_Hayes_(settler)": {"rel2": [[{"http://dbpedia.org/property/predecessor": [["http://dbpedia.org/property/predecessor", "http://dbpedia.org/ontology/successor", "http://dbpedia.org/property/years", "http://dbpedia.org/property/office", "http://dbpedia.org/property/successor"], ["http://dbpedia.org/property/predecessor", "http://dbpedia.org/property/successor"]]}, {"http://dbpedia.org/property/termStart": [[], []]}, {"http://dbpedia.org/property/termEnd": [[], []]}, {"http://dbpedia.org/property/successor": [["http://dbpedia.org/property/predecessor", "http://dbpedia.org/property/termStart", "http://dbpedia.org/property/termEnd", "http://dbpedia.org/ontology/successor", "http://dbpedia.org/property/successor"], ["http://dbpedia.org/ontology/successor", "http://dbpedia.org/property/successor"]]}, {"http://dbpedia.org/ontology/successor": [["http://dbpedia.org/property/predecessor", "http://dbpedia.org/property/termStart", "http://dbpedia.org/property/termEnd", "http://dbpedia.org/ontology/successor", "http://dbpedia.org/property/successor"], ["http://dbpedia.org/ontology/successor", "http://dbpedia.org/property/successor"]]}], [{"http://dbpedia.org/ontology/successor": [["http://dbpedia.org/ontology/successor", "http://dbpedia.org/property/successor"], ["http://dbpedia.org/property/predecessor", "http://dbpedia.org/ontology/successor", "http://dbpedia.org/ontology/child", "http://dbpedia.org/ontology/spouse", "http://dbpedia.org/property/successor"]]}, {"http://dbpedia.org/property/successor": [["http://dbpedia.org/ontology/successor", "http://dbpedia.org/property/successor"], ["http://dbpedia.org/property/predecessor", "http://dbpedia.org/ontology/associate", "http://dbpedia.org/ontology/successor", "http://dbpedia.org/property/alongside", "http://dbpedia.org/property/successor"]]}]], "rel1": [["http://dbpedia.org/property/placeOfDeath", "http://purl.org/linguistics/gold/hypernym", "http://dbpedia.org/property/birthDate", "http://dbpedia.org/property/deathDate", "http://dbpedia.org/ontology/wikiPageWikiLinkText", "http://dbpedia.org/property/years", "http://dbpedia.org/property/residence", "http://dbpedia.org/ontology/restingPlace", "http://www.w3.org/ns/prov#wasDerivedFrom", "http://dbpedia.org/property/spouse", "http://dbpedia.org/property/children", "http://dbpedia.org/property/dateOfBirth", "http://dbpedia.org/property/termEnd", "http://dbpedia.org/property/wikiPageUsesTemplate", "http://dbpedia.org/ontology/child", "http://dbpedia.org/property/restingplace", "http://dbpedia.org/property/birthPlace", "http://dbpedia.org/property/after", "http://dbpedia.org/property/shortDescription", "http://xmlns.com/foaf/0.1/isPrimaryTopicOf", "http://dbpedia.org/property/office", "http://dbpedia.org/ontology/residence", "http://dbpedia.org/property/predecessor", "http://dbpedia.org/ontology/deathYear", "http://dbpedia.org/property/placeOfBirth", "http://dbpedia.org/property/name", "http://purl.org/dc/terms/subject", "http://purl.org/dc/elements/1.1/description", "http://dbpedia.org/ontology/abstract", "http://dbpedia.org/property/termStart", "http://dbpedia.org/ontology/wikiPageID", "http://dbpedia.org/property/deathPlace", "http://www.w3.org/1999/02/22-rdf-syntax-ns#type", "http://dbpedia.org/ontology/deathPlace", "http://dbpedia.org/ontology/birthYear", "http://www.w3.org/2000/01/rdf-schema#label", "http://dbpedia.org/ontology/birthDate", "http://dbpedia.org/property/title", "http://xmlns.com/foaf/0.1/givenName", "http://dbpedia.org/ontology/orderInOffice", "http://www.w3.org/2000/01/rdf-schema#comment", "http://dbpedia.org/property/dateOfDeath", "http://dbpedia.org/ontology/birthPlace", "http://xmlns.com/foaf/0.1/surname", "http://dbpedia.org/ontology/wikiPageWikiLink", "http://dbpedia.org/ontology/wikiPageOutDegree", "http://dbpedia.org/property/before", "http://dbpedia.org/ontology/wikiPageLength", "http://dbpedia.org/ontology/deathDate", "http://dbpedia.org/ontology/successor", "http://xmlns.com/foaf/0.1/name", "http://dbpedia.org/ontology/wikiPageRevisionID", "http://dbpedia.org/property/with", "http://www.w3.org/2002/07/owl#sameAs", "http://dbpedia.org/property/successor"], ["http://xmlns.com/foaf/0.1/primaryTopic", "http://dbpedia.org/ontology/wikiPageDisambiguates", "http://dbpedia.org/property/alongside", "http://dbpedia.org/ontology/wikiPageWikiLink", "http://dbpedia.org/property/successor", "http://dbpedia.org/property/after", "http://dbpedia.org/ontology/successor", "http://dbpedia.org/property/predecessor", "http://dbpedia.org/property/before", "http://dbpedia.org/property/with", "http://dbpedia.org/ontology/spouse", "http://dbpedia.org/ontology/associate"]]}}, "sparql_template_id": 303, "entity": ["http://dbpedia.org/resource/Samuel_Hayes_(settler)"], "path": ["+http://dbpedia.org/ontology/successor", "+http://dbpedia.org/ontology/restingPlace"], "_id": "fa9fedea238d4402b21a174c49cb2e2b", "constraints": {"?x": "http://www.w3.org/1999/02/22-rdf-syntax-ns#type"}}]